<?xml version="1.0" encoding="UTF-8"?>

<meandata>
	<interval begin="0" end="10000" id="whatever">
		<edge id="350046860#0" traveltime="25.5966497292"/>
		<edge id="-23785404" traveltime="6.32884047102"/>
		<edge id="-23785401" traveltime="7.20529007154"/>
		<edge id="162845094" traveltime="1.10292037238"/>
		<edge id="162845096" traveltime="0.952186737459"/>
		<edge id="162845090" traveltime="1.0358700457"/>
		<edge id="162845091" traveltime="0.619554734802"/>
		<edge id="9702321#0" traveltime="2.52354962927"/>
		<edge id="9702321#1" traveltime="4.86748237898"/>
		<edge id="31778224" traveltime="12.4487124362"/>
		<edge id="31778222" traveltime="7.3273580178"/>
		<edge id="31778223" traveltime="5.27957939608"/>
		<edge id="31778221" traveltime="7.97864575017"/>
		<edge id="24660974" traveltime="75.0619501291"/>
		<edge id="350046860#1" traveltime="9.3154577135"/>
		<edge id="24660973" traveltime="24.2311045771"/>
		<edge id="-243046552#1" traveltime="9.80305146532"/>
		<edge id="-243046552#0" traveltime="11.1779150418"/>
		<edge id="-23841670#2" traveltime="11.7021999743"/>
		<edge id="-23841670#0" traveltime="18.7025852267"/>
		<edge id="-23841670#1" traveltime="22.7014518403"/>
		<edge id="-31778222" traveltime="8.82228770442"/>
		<edge id="-31778223" traveltime="5.35312185993"/>
		<edge id="-31778221" traveltime="6.67178930748"/>
		<edge id="23689517#0" traveltime="18.675553955"/>
		<edge id="23689517#1" traveltime="11.7746835963"/>
		<edge id="-23568752#1" traveltime="2.55765906732"/>
		<edge id="-23568752#0" traveltime="0.708208513769"/>
		<edge id="28039419#2" traveltime="6.04096849086"/>
		<edge id="23785447#1" traveltime="0.662451576742"/>
		<edge id="23785447#0" traveltime="12.5989328549"/>
		<edge id="24013895" traveltime="3.98934243445"/>
		<edge id="443977183#3" traveltime="13.6615564703"/>
		<edge id="-28262964" traveltime="1.04260842215"/>
		<edge id="23695668#2" traveltime="7.99081788172"/>
		<edge id="23695668#3" traveltime="12.9837946307"/>
		<edge id="23695668#0" traveltime="0.999164782335"/>
		<edge id="23695668#1" traveltime="0.255926341228"/>
		<edge id="23695668#6" traveltime="0.00648218584276"/>
		<edge id="23695668#4" traveltime="1.76797477674"/>
		<edge id="23695668#5" traveltime="15.681811021"/>
		<edge id="453712612" traveltime="4.64613481265"/>
		<edge id="453712611" traveltime="0.177593106519"/>
		<edge id="-28510481" traveltime="19.8989075711"/>
		<edge id="28120211#0" traveltime="15.7087439944"/>
		<edge id="23603945#0" traveltime="1.60595193939"/>
		<edge id="23603945#3" traveltime="0.183427045451"/>
		<edge id="23603945#2" traveltime="3.93194114615"/>
		<edge id="23603945#5" traveltime="0.424786699358"/>
		<edge id="23603945#4" traveltime="0.293138212967"/>
		<edge id="-28510466" traveltime="8.54565247203"/>
		<edge id="23689372#3" traveltime="0.350044505791"/>
		<edge id="23689372#2" traveltime="1.09888286466"/>
		<edge id="23689372#1" traveltime="10.8948311529"/>
		<edge id="23689372#0" traveltime="0.40492275029"/>
		<edge id="23689372#6" traveltime="0.306184817888"/>
		<edge id="23689372#5" traveltime="1.95832416203"/>
		<edge id="23689372#4" traveltime="0.722492863541"/>
		<edge id="217904127" traveltime="13.1190153702"/>
		<edge id="9702321#2" traveltime="0.938902936328"/>
		<edge id="40856228" traveltime="2.39398643014"/>
		<edge id="193664683#0" traveltime="1.37451815577"/>
		<edge id="193664683#1" traveltime="0.819652525601"/>
		<edge id="242254196" traveltime="5.9968920776"/>
		<edge id="242254197" traveltime="2.19743233376"/>
		<edge id="24260113#0" traveltime="10.3716939061"/>
		<edge id="24260113#1" traveltime="2.63808584708"/>
		<edge id="-24228720#10" traveltime="6.07630505913"/>
		<edge id="-24228720#11" traveltime="0.269538165299"/>
		<edge id="252667982" traveltime="0.882884876928"/>
		<edge id="252667986" traveltime="2.01620373821"/>
		<edge id="252667985" traveltime="0.455799402299"/>
		<edge id="358227398#2" traveltime="0.00878277802001"/>
		<edge id="358227398#1" traveltime="0.216149133335"/>
		<edge id="358227398#0" traveltime="1.30773810764"/>
		<edge id="435219533#5" traveltime="9.14375457584"/>
		<edge id="435219533#4" traveltime="3.69097814893"/>
		<edge id="435219533#1" traveltime="0.162713356411"/>
		<edge id="435219533#0" traveltime="9.52790827307"/>
		<edge id="435219533#3" traveltime="7.8869082931"/>
		<edge id="435219533#2" traveltime="3.36521931447"/>
		<edge id="23785470#5" traveltime="1.80751153133"/>
		<edge id="23785470#4" traveltime="3.98675501583"/>
		<edge id="31520099#0" traveltime="0.558880139118"/>
		<edge id="31520099#1" traveltime="6.07693724182"/>
		<edge id="23785470#3" traveltime="8.70379497605"/>
		<edge id="23785470#2" traveltime="2.8734931798"/>
		<edge id="31519922#0" traveltime="6.10508363992"/>
		<edge id="24031683#0" traveltime="0.254057572028"/>
		<edge id="24031683#1" traveltime="16.3778311652"/>
		<edge id="24031683#2" traveltime="8.55141144466"/>
		<edge id="31519923#0" traveltime="1.12224893566"/>
		<edge id="31519923#1" traveltime="0.166071196337"/>
		<edge id="196563529#0" traveltime="27.6069076431"/>
		<edge id="196563529#1" traveltime="0.106594064711"/>
		<edge id="-23569686" traveltime="6.81349512694"/>
		<edge id="243040722" traveltime="0.265660289776"/>
		<edge id="243040725" traveltime="0.0872432436038"/>
		<edge id="-23569688" traveltime="6.4734582839"/>
		<edge id="243040726" traveltime="0.377314862715"/>
		<edge id="-27268906" traveltime="18.4363690288"/>
		<edge id="-23569730" traveltime="4.36450335601"/>
		<edge id="-350046877" traveltime="0.577090683941"/>
		<edge id="23551884#3" traveltime="0.274117427364"/>
		<edge id="23551884#2" traveltime="5.12142578423"/>
		<edge id="23551884#1" traveltime="0.346038812449"/>
		<edge id="23551884#0" traveltime="0.307314003722"/>
		<edge id="-350046878" traveltime="0.435259869644"/>
		<edge id="-31778224" traveltime="13.357130895"/>
		<edge id="4684688" traveltime="21.8172101051"/>
		<edge id="4684687" traveltime="32.4588223636"/>
		<edge id="-23570763#0" traveltime="2.5466899719"/>
		<edge id="-23570763#1" traveltime="6.55866437417"/>
		<edge id="-23570763#2" traveltime="14.3580209344"/>
		<edge id="-23570763#3" traveltime="1.06673240026"/>
		<edge id="-243046552#2" traveltime="0.802895907526"/>
		<edge id="258337284" traveltime="15.1597982206"/>
		<edge id="-23689459#1" traveltime="3.04845279467"/>
		<edge id="-23689459#0" traveltime="1.03652788083"/>
		<edge id="-23689459#3" traveltime="9.84760911446"/>
		<edge id="-23689459#2" traveltime="21.9422664023"/>
		<edge id="-23689459#5" traveltime="3.90572382257"/>
		<edge id="-23689459#4" traveltime="6.09050663694"/>
		<edge id="23912424" traveltime="10.1836929453"/>
		<edge id="23681466" traveltime="6.97365751868"/>
		<edge id="45340188" traveltime="20.5776914129"/>
		<edge id="32873313" traveltime="6.34885403806"/>
		<edge id="23570236#1" traveltime="5.10333212118"/>
		<edge id="23570236#0" traveltime="10.1877244162"/>
		<edge id="31509570" traveltime="5.11518741962"/>
		<edge id="-350046860#0" traveltime="21.616317837"/>
		<edge id="-350046860#1" traveltime="7.94518539556"/>
		<edge id="31778241#0" traveltime="12.1439518083"/>
		<edge id="31778241#1" traveltime="12.1571469092"/>
		<edge id="23568566#7" traveltime="0.598285991031"/>
		<edge id="28039419#1" traveltime="0.926271748862"/>
		<edge id="28039419#0" traveltime="0.137599895347"/>
		<edge id="23570731#1" traveltime="10.4491969142"/>
		<edge id="23570731#0" traveltime="0.225307587015"/>
		<edge id="23841660" traveltime="0.0310700805663"/>
		<edge id="279360229#2" traveltime="38.8201156476"/>
		<edge id="279360229#0" traveltime="13.1601672673"/>
		<edge id="279360229#1" traveltime="20.5088813837"/>
		<edge id="365965546#3" traveltime="2.43448797641"/>
		<edge id="365965546#2" traveltime="7.09210511433"/>
		<edge id="31519660#0" traveltime="1.82216978555"/>
		<edge id="31519660#1" traveltime="0.076196997939"/>
		<edge id="-25994897#2" traveltime="15.9810854168"/>
		<edge id="-25994897#0" traveltime="12.3877507151"/>
		<edge id="-25994897#1" traveltime="17.4471132219"/>
		<edge id="-23802588#1" traveltime="9.11662217635"/>
		<edge id="-23802588#0" traveltime="0.916202273715"/>
		<edge id="-23802588#2" traveltime="0.227602729773"/>
		<edge id="261926530#0" traveltime="6.55943236854"/>
		<edge id="261926530#1" traveltime="18.7404962224"/>
		<edge id="261926530#2" traveltime="0.376003367187"/>
		<edge id="261926530#3" traveltime="1.2269674073"/>
		<edge id="23785391" traveltime="22.7361625052"/>
		<edge id="365756274" traveltime="1.19051876473"/>
		<edge id="32113733" traveltime="5.88849200327"/>
		<edge id="9702521" traveltime="2.4514420688"/>
		<edge id="32113736" traveltime="3.64859573574"/>
		<edge id="365965545" traveltime="11.2377060831"/>
		<edge id="365965542" traveltime="0.538679980777"/>
		<edge id="365965540" traveltime="1.99246628611"/>
		<edge id="350046859" traveltime="4.04633320604"/>
		<edge id="-23570218#1" traveltime="0.618550729179"/>
		<edge id="-23570218#0" traveltime="8.90049363475"/>
		<edge id="350046863#9" traveltime="8.79259042566"/>
		<edge id="350046863#8" traveltime="0.0183652057065"/>
		<edge id="350046863#5" traveltime="0.683930413014"/>
		<edge id="24031615#0" traveltime="1.55173804686"/>
		<edge id="24031615#3" traveltime="0.133476627892"/>
		<edge id="24031615#2" traveltime="8.46878126658"/>
		<edge id="350046863#1" traveltime="1.34742632057"/>
		<edge id="350046863#0" traveltime="4.87704614603"/>
		<edge id="350046863#3" traveltime="13.6014411193"/>
		<edge id="350046863#2" traveltime="0.0936184027671"/>
		<edge id="-23785464#2" traveltime="2.25935033208"/>
		<edge id="-23785464#0" traveltime="2.34419776985"/>
		<edge id="-23785464#1" traveltime="12.5656883423"/>
		<edge id="27268908#2" traveltime="0.166143441109"/>
		<edge id="27268908#1" traveltime="18.5893070097"/>
		<edge id="27268908#0" traveltime="1.85726508099"/>
		<edge id="25994509" traveltime="10.7019476494"/>
		<edge id="31516858" traveltime="0.0113331923861"/>
		<edge id="23604091#6" traveltime="0.338269175367"/>
		<edge id="23604091#4" traveltime="9.47344247189"/>
		<edge id="23604091#5" traveltime="3.41923012706"/>
		<edge id="23604091#2" traveltime="2.70722423727"/>
		<edge id="23604091#3" traveltime="1.46475719552"/>
		<edge id="23604091#0" traveltime="1.00338809377"/>
		<edge id="23604091#1" traveltime="5.63982741431"/>
		<edge id="243040730" traveltime="0.0225178653676"/>
		<edge id="243040731" traveltime="0.647766922752"/>
		<edge id="243040736" traveltime="1.70474228179"/>
		<edge id="243040737" traveltime="5.39650150259"/>
		<edge id="243040734" traveltime="1.83367293019"/>
		<edge id="242254206#1" traveltime="1.64760184174"/>
		<edge id="242254206#0" traveltime="0.605401576122"/>
		<edge id="395691394#1" traveltime="18.0936537738"/>
		<edge id="395691394#0" traveltime="15.0069461105"/>
		<edge id="350046872#2" traveltime="3.85327548296"/>
		<edge id="350046872#1" traveltime="1.23742388081"/>
		<edge id="350046872#0" traveltime="0.200100208731"/>
		<edge id="9702507#1" traveltime="0.393640270886"/>
		<edge id="455252241" traveltime="40.1695823113"/>
		<edge id="23603945#1" traveltime="1.33161329619"/>
		<edge id="25994523#2" traveltime="1.30209949755"/>
		<edge id="27330500" traveltime="6.87577170161"/>
		<edge id="28120211#1" traveltime="0.517626660618"/>
		<edge id="-261926528#2" traveltime="9.27624653956"/>
		<edge id="-261926528#1" traveltime="13.7142175992"/>
		<edge id="-261926528#0" traveltime="4.86807143082"/>
		<edge id="31628867" traveltime="10.1607258553"/>
		<edge id="162845077" traveltime="0.899692318257"/>
		<edge id="162845075" traveltime="0.68071555982"/>
		<edge id="253118241" traveltime="12.0332368278"/>
		<edge id="24260364" traveltime="2.9768805186"/>
		<edge id="-23818185" traveltime="17.2033000147"/>
		<edge id="31778240" traveltime="0.178927510701"/>
		<edge id="261058031#1" traveltime="15.4657552223"/>
		<edge id="23604115" traveltime="0.481626321345"/>
		<edge id="23841670#0" traveltime="14.0373345755"/>
		<edge id="23841670#1" traveltime="25.035564465"/>
		<edge id="233189682#2" traveltime="4.78300166502"/>
		<edge id="233189682#3" traveltime="0.431247363347"/>
		<edge id="233189682#0" traveltime="17.7049340196"/>
		<edge id="233189682#1" traveltime="1.55796376073"/>
		<edge id="233189682#4" traveltime="10.8076084296"/>
		<edge id="31697490" traveltime="1.83405442781"/>
		<edge id="24661103#0" traveltime="0.189948551352"/>
		<edge id="24661103#1" traveltime="13.5928609497"/>
		<edge id="252667984#1" traveltime="0.823995583905"/>
		<edge id="252667984#0" traveltime="0.938007451512"/>
		<edge id="23947375" traveltime="5.30293443638"/>
		<edge id="215446161#0" traveltime="1.03692590769"/>
		<edge id="-23570800#0" traveltime="9.31053249417"/>
		<edge id="-23570800#1" traveltime="10.4009915008"/>
		<edge id="46714771" traveltime="0.349477469769"/>
		<edge id="365965551#1" traveltime="21.8296436635"/>
		<edge id="365965551#0" traveltime="0.122843424051"/>
		<edge id="97405291#4" traveltime="3.83845904223"/>
		<edge id="97405291#5" traveltime="84.0856101398"/>
		<edge id="97405291#6" traveltime="3.51119191424"/>
		<edge id="97405291#0" traveltime="11.965382188"/>
		<edge id="97405291#1" traveltime="2.44246880317"/>
		<edge id="97405291#2" traveltime="5.89999895222"/>
		<edge id="97405291#3" traveltime="2.44793305651"/>
		<edge id="32113740#0" traveltime="8.67925523433"/>
		<edge id="32113740#1" traveltime="10.0185252199"/>
		<edge id="32113740#2" traveltime="0.561227143854"/>
		<edge id="365782826#0" traveltime="7.07116697276"/>
		<edge id="365965539#1" traveltime="7.30340771094"/>
		<edge id="23603932" traveltime="16.8912849545"/>
		<edge id="48099019#1" traveltime="10.8753966063"/>
		<edge id="365965539#0" traveltime="9.08065997976"/>
		<edge id="48099019#0" traveltime="40.6988676876"/>
		<edge id="23947358#0" traveltime="11.0648759785"/>
		<edge id="23947358#1" traveltime="12.5696669239"/>
		<edge id="27330490#1" traveltime="49.4458312533"/>
		<edge id="27330490#0" traveltime="9.62286577067"/>
		<edge id="-358228120#1" traveltime="12.4155681508"/>
		<edge id="-358228120#0" traveltime="4.47647227717"/>
		<edge id="23570193" traveltime="4.9380110679"/>
		<edge id="-243040722" traveltime="0.346335304568"/>
		<edge id="9702467" traveltime="10.4349074459"/>
		<edge id="9702464" traveltime="0.0963065188192"/>
		<edge id="9702507#0" traveltime="2.2199435867"/>
		<edge id="-285676729" traveltime="11.4313525777"/>
		<edge id="23785396#2" traveltime="3.70640514"/>
		<edge id="23785396#0" traveltime="6.300011503"/>
		<edge id="23785396#1" traveltime="6.21008768878"/>
		<edge id="25994511" traveltime="11.3464957654"/>
		<edge id="31516862" traveltime="13.8275166816"/>
		<edge id="25994515" traveltime="13.690645606"/>
		<edge id="215446161#1" traveltime="1.2746657625"/>
		<edge id="25994519" traveltime="17.1352045966"/>
		<edge id="23590678#2" traveltime="46.7028254537"/>
		<edge id="23590678#1" traveltime="20.2345144882"/>
		<edge id="23590678#0" traveltime="4.7607850876"/>
		<edge id="-23947367#1" traveltime="1.40365988757"/>
		<edge id="243040709" traveltime="0.368978007241"/>
		<edge id="-27330500" traveltime="4.94726074221"/>
		<edge id="243040720#2" traveltime="0.546746962475"/>
		<edge id="243040720#0" traveltime="5.48906446966"/>
		<edge id="243040720#1" traveltime="1.29966191667"/>
		<edge id="-23570103#1" traveltime="7.12359391647"/>
		<edge id="-23785472" traveltime="4.46595759184"/>
		<edge id="31519919#1" traveltime="4.57994400772"/>
		<edge id="31519919#0" traveltime="0.591479387757"/>
		<edge id="350046863#10" traveltime="7.24449169252"/>
		<edge id="90282232" traveltime="4.72090758314"/>
		<edge id="46714506#0" traveltime="0.415730409808"/>
		<edge id="46714506#1" traveltime="0.88243189101"/>
		<edge id="-24031601#2" traveltime="10.507311361"/>
		<edge id="-24031601#0" traveltime="4.82330189638"/>
		<edge id="-24031601#1" traveltime="15.8321059806"/>
		<edge id="261926528#2" traveltime="6.82220799433"/>
		<edge id="261926528#1" traveltime="11.5305033477"/>
		<edge id="261926528#0" traveltime="16.0987154604"/>
		<edge id="28348766" traveltime="12.3140248972"/>
		<edge id="28348764" traveltime="10.2882812705"/>
		<edge id="449732385" traveltime="4.78430204536"/>
		<edge id="449732384" traveltime="3.77635211894"/>
		<edge id="449732383" traveltime="68.8675877991"/>
		<edge id="27268911#1" traveltime="12.5518309277"/>
		<edge id="261056934#1" traveltime="3.73439953862"/>
		<edge id="23818221#0" traveltime="7.27032943297"/>
		<edge id="23818221#1" traveltime="0.932177700897"/>
		<edge id="23570750#4" traveltime="2.18890418912"/>
		<edge id="23570750#2" traveltime="0.865955467858"/>
		<edge id="23570750#3" traveltime="8.21923942318"/>
		<edge id="23570750#0" traveltime="0.730289456267"/>
		<edge id="23570750#1" traveltime="11.9225998471"/>
		<edge id="24031706#0" traveltime="1.11211709337"/>
		<edge id="24031706#1" traveltime="7.26383372734"/>
		<edge id="24031706#2" traveltime="10.3965677347"/>
		<edge id="24031706#3" traveltime="18.8346075914"/>
		<edge id="23818185" traveltime="14.654166503"/>
		<edge id="23802586#2" traveltime="0.517088689943"/>
		<edge id="23802586#1" traveltime="17.0989337852"/>
		<edge id="23802586#0" traveltime="0.685008327658"/>
		<edge id="25994523#0" traveltime="0.167433538509"/>
		<edge id="32038120#0" traveltime="7.63106759652"/>
		<edge id="32038120#1" traveltime="10.3133212992"/>
		<edge id="32038120#2" traveltime="0.881336023088"/>
		<edge id="365965552#0" traveltime="0.484281040743"/>
		<edge id="365965552#1" traveltime="0.0258371322989"/>
		<edge id="23802588#1" traveltime="9.21100440356"/>
		<edge id="23802588#0" traveltime="0.578874003674"/>
		<edge id="23802588#2" traveltime="0.731812222433"/>
		<edge id="23802565#6" traveltime="6.62076344608"/>
		<edge id="403906246#0" traveltime="3.0634895955"/>
		<edge id="403906246#1" traveltime="0.876048179147"/>
		<edge id="32038116#3" traveltime="6.35721852343"/>
		<edge id="32038116#2" traveltime="0.0214501169586"/>
		<edge id="32038116#1" traveltime="3.95068754453"/>
		<edge id="32038116#0" traveltime="0.0132902766791"/>
		<edge id="32038116#4" traveltime="21.0235978581"/>
		<edge id="31519662#4" traveltime="5.09847222889"/>
		<edge id="31519662#5" traveltime="0.143730628267"/>
		<edge id="31519662#0" traveltime="0.525672004159"/>
		<edge id="31519662#1" traveltime="3.97338170607"/>
		<edge id="31519662#2" traveltime="4.17318774507"/>
		<edge id="31519662#3" traveltime="1.46754858111"/>
		<edge id="-9702304#4" traveltime="11.3120251859"/>
		<edge id="-25994513#1" traveltime="1.0267377345"/>
		<edge id="-25994513#0" traveltime="11.0517231597"/>
		<edge id="23695675" traveltime="1.30394799807"/>
		<edge id="23603923" traveltime="9.84701074042"/>
		<edge id="388910547" traveltime="3.61062066932"/>
		<edge id="24031601#2" traveltime="22.9641360387"/>
		<edge id="-453955195#1" traveltime="5.37609465021"/>
		<edge id="24031601#0" traveltime="6.03609630372"/>
		<edge id="24031601#1" traveltime="15.0111538167"/>
		<edge id="217904125#1" traveltime="0.423569958989"/>
		<edge id="217904125#0" traveltime="0.0555499299206"/>
		<edge id="31520213" traveltime="0.255659669913"/>
		<edge id="90282216#1" traveltime="2.00587446634"/>
		<edge id="90282216#0" traveltime="0.303216151958"/>
		<edge id="23785499#0" traveltime="16.6066123257"/>
		<edge id="23785499#1" traveltime="5.15173550297"/>
		<edge id="365756273#0" traveltime="8.48887604717"/>
		<edge id="365756273#1" traveltime="29.3860519258"/>
		<edge id="23551895#1" traveltime="9.97889885818"/>
		<edge id="23551895#0" traveltime="0.172546021684"/>
		<edge id="217904156" traveltime="3.54042777168"/>
		<edge id="217904157" traveltime="14.9340057068"/>
		<edge id="9702470" traveltime="1.29403677895"/>
		<edge id="-257657826#0" traveltime="9.95162722543"/>
		<edge id="-257657826#1" traveltime="17.3602739285"/>
		<edge id="243040743#1" traveltime="1.03927252146"/>
		<edge id="243040743#0" traveltime="0.832564091572"/>
		<edge id="-285676731" traveltime="5.34543771309"/>
		<edge id="-23818206" traveltime="23.4580846163"/>
		<edge id="28510466" traveltime="15.9506894595"/>
		<edge id="25994521" traveltime="6.41564784299"/>
		<edge id="365787222#0" traveltime="8.75322652304"/>
		<edge id="365787222#1" traveltime="14.0817446533"/>
		<edge id="24249433#0" traveltime="2.7052519884"/>
		<edge id="24249433#1" traveltime="1.36226991533"/>
		<edge id="215446174" traveltime="1.34042533054"/>
		<edge id="-24260015" traveltime="24.4644152904"/>
		<edge id="243040717#1" traveltime="17.2554519136"/>
		<edge id="243040717#2" traveltime="0.537551866723"/>
		<edge id="243040714" traveltime="0.53625904412"/>
		<edge id="243040716" traveltime="3.10557402856"/>
		<edge id="28510481" traveltime="21.3099404483"/>
		<edge id="-23785487#3" traveltime="21.5567539881"/>
		<edge id="-23785487#2" traveltime="0.368244472973"/>
		<edge id="-23785487#1" traveltime="10.4667250981"/>
		<edge id="-23785487#0" traveltime="4.47090229233"/>
		<edge id="-23785487#7" traveltime="9.00224901842"/>
		<edge id="-23785487#6" traveltime="0.211982401063"/>
		<edge id="-23785487#5" traveltime="9.69324495818"/>
		<edge id="-23785487#4" traveltime="10.7073406263"/>
		<edge id="24791131" traveltime="32.3617864656"/>
		<edge id="27921855" traveltime="4.54858818623"/>
		<edge id="23590694" traveltime="9.78918022572"/>
		<edge id="-372623525#1" traveltime="8.70663792074"/>
		<edge id="-372623525#0" traveltime="13.4249375671"/>
		<edge id="261056935#1" traveltime="0.60391341633"/>
		<edge id="261056935#0" traveltime="6.59644328794"/>
		<edge id="261056935#2" traveltime="0.500759547644"/>
		<edge id="-23681482#1" traveltime="0.574213921908"/>
		<edge id="-23681482#0" traveltime="10.2965511691"/>
		<edge id="-23681482#2" traveltime="4.41917498863"/>
		<edge id="31509571#4" traveltime="1.41526016601"/>
		<edge id="31509571#2" traveltime="0.583049405695"/>
		<edge id="31509571#3" traveltime="5.62797529184"/>
		<edge id="31509571#0" traveltime="0.944842846269"/>
		<edge id="31509571#1" traveltime="4.12695042527"/>
		<edge id="90282223" traveltime="2.94290346555"/>
		<edge id="90282221" traveltime="0.328943557552"/>
		<edge id="-445309968#2" traveltime="17.9295727775"/>
		<edge id="-445309968#3" traveltime="0.940786971178"/>
		<edge id="-445309968#0" traveltime="2.17018679919"/>
		<edge id="100682788" traveltime="6.66338567797"/>
		<edge id="365787228" traveltime="2.33178323317"/>
		<edge id="365787224" traveltime="0.259673892119"/>
		<edge id="365787226" traveltime="5.9578177676"/>
		<edge id="365787221" traveltime="7.45638966426"/>
		<edge id="365787220" traveltime="3.05826577807"/>
		<edge id="365787223" traveltime="7.36596637981"/>
		<edge id="100682784" traveltime="7.04073870239"/>
		<edge id="-23570193" traveltime="6.43173988389"/>
		<edge id="23819116" traveltime="12.1632622475"/>
		<edge id="101233479" traveltime="19.3716606667"/>
		<edge id="220958540#5" traveltime="2.06663988886"/>
		<edge id="220958540#4" traveltime="7.9119364608"/>
		<edge id="220958540#6" traveltime="22.0632901139"/>
		<edge id="220958540#1" traveltime="1.47947816068"/>
		<edge id="220958540#0" traveltime="1.21243488289"/>
		<edge id="220958540#3" traveltime="13.3915556375"/>
		<edge id="220958540#2" traveltime="15.9433673801"/>
		<edge id="23819685" traveltime="8.8786831814"/>
		<edge id="403906247#1" traveltime="4.35202494249"/>
		<edge id="403906247#0" traveltime="2.70205900334"/>
		<edge id="403906247#2" traveltime="2.26064112234"/>
		<edge id="32038117" traveltime="0.00478491279357"/>
		<edge id="32038114" traveltime="5.36926155156"/>
		<edge id="24031618" traveltime="10.9273132579"/>
		<edge id="32038113" traveltime="0.145551352223"/>
		<edge id="23785470#1" traveltime="5.06575802639"/>
		<edge id="-23785440" traveltime="9.84229176418"/>
		<edge id="23785470#0" traveltime="1.12236099976"/>
		<edge id="31520099#2" traveltime="7.9516519286"/>
		<edge id="365965543#0" traveltime="0.145360539383"/>
		<edge id="365965543#1" traveltime="0.264694540656"/>
		<edge id="453955196#3" traveltime="0.18183009223"/>
		<edge id="453955196#2" traveltime="8.86858200613"/>
		<edge id="453955196#1" traveltime="3.58211355289"/>
		<edge id="453955196#0" traveltime="6.04007708883"/>
		<edge id="23572221" traveltime="0.0280225217202"/>
		<edge id="358227397" traveltime="6.67856765128"/>
		<edge id="23590688#0" traveltime="8.14421708798"/>
		<edge id="23590688#1" traveltime="1.5686553448"/>
		<edge id="358227400" traveltime="2.80546012925"/>
		<edge id="90282234#2" traveltime="1.49298876281"/>
		<edge id="90282234#1" traveltime="0.540290485931"/>
		<edge id="90282234#0" traveltime="3.8648965647"/>
		<edge id="-365756273#0" traveltime="4.34687907636"/>
		<edge id="-365756273#1" traveltime="31.3155586284"/>
		<edge id="350046876#2" traveltime="1.24954114412"/>
		<edge id="350046876#1" traveltime="0.265760126686"/>
		<edge id="350046876#0" traveltime="22.5672547204"/>
		<edge id="31519921" traveltime="10.3411635924"/>
		<edge id="-23785475#0" traveltime="11.0187058557"/>
		<edge id="-23785475#1" traveltime="19.2391163975"/>
		<edge id="-23912424" traveltime="12.2396388682"/>
		<edge id="24228800#1" traveltime="3.17045144794"/>
		<edge id="24228800#0" traveltime="12.045068683"/>
		<edge id="24228800#2" traveltime="5.6113339033"/>
		<edge id="31520553#1" traveltime="1.2471626528"/>
		<edge id="31520553#0" traveltime="2.77596662822"/>
		<edge id="-23689552#1" traveltime="9.33507691883"/>
		<edge id="23570208" traveltime="6.82899147617"/>
		<edge id="243040739#0" traveltime="1.63530943347"/>
		<edge id="243040739#1" traveltime="9.53196499715"/>
		<edge id="243040739#2" traveltime="1.63105972715"/>
		<edge id="243040739#3" traveltime="15.8726955277"/>
		<edge id="24252423#1" traveltime="11.7575447814"/>
		<edge id="24252423#0" traveltime="7.72417933117"/>
		<edge id="24252423#3" traveltime="0.016217557834"/>
		<edge id="24252423#2" traveltime="1.25419168317"/>
		<edge id="24252423#4" traveltime="1.51177261241"/>
		<edge id="350046881" traveltime="0.895979771165"/>
		<edge id="350046880" traveltime="1.33693643628"/>
		<edge id="220958548#1" traveltime="0.645968919514"/>
		<edge id="25994513#1" traveltime="1.46175822313"/>
		<edge id="25994513#0" traveltime="7.49536510866"/>
		<edge id="235138538" traveltime="16.6919050575"/>
		<edge id="261056934#0" traveltime="4.5592869434"/>
		<edge id="27268911#0" traveltime="12.2113019518"/>
		<edge id="-23570799#1" traveltime="4.32129773021"/>
		<edge id="220958549#4" traveltime="1.80704011059"/>
		<edge id="220958549#5" traveltime="7.81895707303"/>
		<edge id="220958549#6" traveltime="11.9121553626"/>
		<edge id="-23570799#0" traveltime="6.16631621874"/>
		<edge id="220958549#0" traveltime="7.12720605402"/>
		<edge id="220958549#1" traveltime="11.4529916809"/>
		<edge id="220958549#2" traveltime="8.90161209548"/>
		<edge id="220958549#3" traveltime="10.3727717406"/>
		<edge id="-45547151" traveltime="0.0997390343374"/>
		<edge id="23785428#3" traveltime="0.687441671301"/>
		<edge id="23785428#0" traveltime="2.81358160084"/>
		<edge id="23785428#1" traveltime="0.76379891091"/>
		<edge id="-28348766" traveltime="8.50452484072"/>
		<edge id="-28348764" traveltime="12.2928875351"/>
		<edge id="-23572294#1" traveltime="16.7513863902"/>
		<edge id="-31983270" traveltime="0.227208755719"/>
		<edge id="-23572294#2" traveltime="11.1977266442"/>
		<edge id="90282207#0" traveltime="6.48079533288"/>
		<edge id="46714801" traveltime="0.189113003801"/>
		<edge id="243040732#1" traveltime="0.863869621886"/>
		<edge id="243040732#0" traveltime="2.99614372708"/>
		<edge id="443564911" traveltime="0.0103352392697"/>
		<edge id="243040729" traveltime="1.46445279727"/>
		<edge id="243040728" traveltime="1.38919846465"/>
		<edge id="31519923#2" traveltime="0.0862474648046"/>
		<edge id="-443977183#8" traveltime="8.37484303975"/>
		<edge id="-443977183#9" traveltime="0.136300581511"/>
		<edge id="324330499" traveltime="2.65826801088"/>
		<edge id="-443977183#7" traveltime="8.51458435079"/>
		<edge id="24252067" traveltime="6.97454322543"/>
		<edge id="-443977183#5" traveltime="11.6272522982"/>
		<edge id="-443977183#2" traveltime="0.788154090833"/>
		<edge id="-443977183#3" traveltime="8.68626760798"/>
		<edge id="-443977183#0" traveltime="2.79222553978"/>
		<edge id="-443977183#1" traveltime="9.31424245334"/>
		<edge id="-31778225#4" traveltime="16.6257478702"/>
		<edge id="-31778225#5" traveltime="15.8523513449"/>
		<edge id="-31778225#6" traveltime="16.2348847515"/>
		<edge id="-31778225#7" traveltime="14.3974998514"/>
		<edge id="-31778225#0" traveltime="4.53854152895"/>
		<edge id="-31778225#1" traveltime="5.99058031703"/>
		<edge id="-31778225#2" traveltime="12.3781852228"/>
		<edge id="-31778225#3" traveltime="0.332128044225"/>
		<edge id="24445036" traveltime="0.3726374489"/>
		<edge id="24445037" traveltime="0.807710604283"/>
		<edge id="23689454#0" traveltime="1.11714184095"/>
		<edge id="23689454#1" traveltime="3.77576458621"/>
		<edge id="23689454#2" traveltime="1.06254283602"/>
		<edge id="23570417#6" traveltime="0.304025525951"/>
		<edge id="23570417#7" traveltime="0.667420839871"/>
		<edge id="23570417#4" traveltime="4.40420881654"/>
		<edge id="23570417#5" traveltime="5.58472939562"/>
		<edge id="23570417#2" traveltime="0.570317178718"/>
		<edge id="23570417#3" traveltime="6.45908219324"/>
		<edge id="23570417#0" traveltime="3.39889611285"/>
		<edge id="23570417#1" traveltime="0.420991528425"/>
		<edge id="90282215" traveltime="2.0376352215"/>
		<edge id="395691394#2" traveltime="0.516059668575"/>
		<edge id="23570417#8" traveltime="0.85342418836"/>
		<edge id="23570417#9" traveltime="3.66081717973"/>
		<edge id="100682799" traveltime="13.256458701"/>
		<edge id="100682794" traveltime="10.3409294969"/>
		<edge id="365787232" traveltime="7.57637020781"/>
		<edge id="100682792" traveltime="0.780029603487"/>
		<edge id="100682793" traveltime="0.295965447453"/>
		<edge id="25995141#1" traveltime="19.2975523277"/>
		<edge id="25995141#0" traveltime="1.97813357437"/>
		<edge id="25995141#3" traveltime="27.8877809136"/>
		<edge id="25995141#2" traveltime="1.67430600867"/>
		<edge id="25995141#5" traveltime="2.38948596059"/>
		<edge id="25995141#4" traveltime="70.2816870154"/>
		<edge id="31741033" traveltime="29.6508059671"/>
		<edge id="31741034" traveltime="11.0194617584"/>
		<edge id="453955195#0" traveltime="0.0124462294932"/>
		<edge id="453955195#1" traveltime="15.9865318042"/>
		<edge id="-459587081#3" traveltime="8.44169909674"/>
		<edge id="-459587081#2" traveltime="0.0274433855948"/>
		<edge id="-459587081#1" traveltime="0.408251467943"/>
		<edge id="-459587081#0" traveltime="6.23618816969"/>
		<edge id="31741102" traveltime="28.95635935"/>
		<edge id="-45340188" traveltime="28.4536097588"/>
		<edge id="233189681" traveltime="2.45968054094"/>
		<edge id="233189680" traveltime="1.38947324652"/>
		<edge id="-27330490#1" traveltime="61.0467073177"/>
		<edge id="-27330490#0" traveltime="7.4197971836"/>
		<edge id="9702508#1" traveltime="5.8938413789"/>
		<edge id="9702508#0" traveltime="3.3614552399"/>
		<edge id="31516859#1" traveltime="0.025585296087"/>
		<edge id="31516859#0" traveltime="3.95759503052"/>
		<edge id="-220958541" traveltime="33.894936289"/>
		<edge id="349878277" traveltime="1.172455976"/>
		<edge id="349878275" traveltime="0.290390782791"/>
		<edge id="349878274" traveltime="0.74889002806"/>
		<edge id="349878279" traveltime="0.569152409797"/>
		<edge id="243040738#1" traveltime="0.885606461981"/>
		<edge id="243040738#0" traveltime="7.62963421276"/>
		<edge id="243040738#3" traveltime="20.2288835014"/>
		<edge id="243040738#2" traveltime="0.0241551397282"/>
		<edge id="23628792#0" traveltime="9.62190509043"/>
		<edge id="23628792#1" traveltime="8.33543603401"/>
		<edge id="23628792#2" traveltime="0.00635588981136"/>
		<edge id="198847481" traveltime="43.806632067"/>
		<edge id="9702386#1" traveltime="2.17562502317"/>
		<edge id="9702386#0" traveltime="9.09525407604"/>
		<edge id="196563502" traveltime="14.1914324194"/>
		<edge id="23570787" traveltime="0.127088977427"/>
		<edge id="23570785" traveltime="0.512737805468"/>
		<edge id="23628746" traveltime="4.10881204636"/>
		<edge id="220958548#0" traveltime="1.22120392353"/>
		<edge id="31952248" traveltime="16.0214022537"/>
		<edge id="220958548#2" traveltime="0.523860448449"/>
		<edge id="25994897#2" traveltime="10.8574771687"/>
		<edge id="25994897#0" traveltime="14.4666970176"/>
		<edge id="25994897#1" traveltime="19.7033214317"/>
		<edge id="40856320" traveltime="27.1072884089"/>
		<edge id="-243040723#1" traveltime="3.8997041487"/>
		<edge id="-243040723#0" traveltime="14.4606541121"/>
		<edge id="-243040723#2" traveltime="1.52938377615"/>
		<edge id="-34305140" traveltime="9.07610113926"/>
		<edge id="31778225#4" traveltime="8.02896173736"/>
		<edge id="31778225#5" traveltime="7.0579389112"/>
		<edge id="31778225#6" traveltime="14.51204296"/>
		<edge id="31778225#7" traveltime="19.7304278544"/>
		<edge id="31778225#0" traveltime="19.0017761496"/>
		<edge id="31778225#1" traveltime="13.476076616"/>
		<edge id="31778225#2" traveltime="14.1527458713"/>
		<edge id="31778225#3" traveltime="0.358782782023"/>
		<edge id="243046552#1" traveltime="12.6150182556"/>
		<edge id="243046552#0" traveltime="7.62482977632"/>
		<edge id="32662619#0" traveltime="19.0122123892"/>
		<edge id="243046552#2" traveltime="1.08710214704"/>
		<edge id="31519920#1" traveltime="0.342274042314"/>
		<edge id="31519920#0" traveltime="6.73835522178"/>
		<edge id="27318139" traveltime="0.927780438695"/>
		<edge id="27318138" traveltime="2.18689286365"/>
		<edge id="9702304#5" traveltime="7.58797719563"/>
		<edge id="-23569651" traveltime="5.09826958912"/>
		<edge id="-23569655" traveltime="8.32516103957"/>
		<edge id="-23502729" traveltime="0.0440195284636"/>
		<edge id="23763161#0" traveltime="18.0058743532"/>
		<edge id="23763161#1" traveltime="10.6723190972"/>
		<edge id="253118240" traveltime="5.37366403079"/>
		<edge id="32662619#1" traveltime="22.9979142324"/>
		<edge id="97405344" traveltime="23.465097711"/>
		<edge id="23569944" traveltime="5.7230202734"/>
		<edge id="30915218" traveltime="13.691360423"/>
		<edge id="30915214" traveltime="24.2353872516"/>
		<edge id="30915217" traveltime="21.1888523899"/>
		<edge id="23568566#6" traveltime="7.67575003902"/>
		<edge id="32662615" traveltime="5.13689294604"/>
		<edge id="32662616" traveltime="14.7600327187"/>
		<edge id="23568566#5" traveltime="1.2042355811"/>
		<edge id="23568566#2" traveltime="7.11083419268"/>
		<edge id="23568566#3" traveltime="1.04697045078"/>
		<edge id="23568566#0" traveltime="3.58942438988"/>
		<edge id="23568566#1" traveltime="1.61373685561"/>
		<edge id="23568566#8" traveltime="2.14656438316"/>
		<edge id="31509573#0" traveltime="4.4818269422"/>
		<edge id="31509573#1" traveltime="15.1195715663"/>
		<edge id="31509573#2" traveltime="4.84919689123"/>
		<edge id="31509573#3" traveltime="1.61897559944"/>
		<edge id="31509573#4" traveltime="2.91242520023"/>
		<edge id="-28039419#2" traveltime="8.13158193763"/>
		<edge id="-28039419#1" traveltime="6.18891603112"/>
		<edge id="-28039419#0" traveltime="0.190379392678"/>
		<edge id="23604035#0" traveltime="4.4939112365"/>
		<edge id="24252066#4" traveltime="0.210081638518"/>
		<edge id="4086172" traveltime="52.2799518428"/>
		<edge id="24252066#0" traveltime="17.0288060876"/>
		<edge id="24252066#1" traveltime="14.2952788254"/>
		<edge id="24252066#2" traveltime="0.799814215026"/>
		<edge id="24252066#3" traveltime="1.54930011966"/>
		<edge id="23628728#2" traveltime="0.701459010995"/>
		<edge id="23628728#1" traveltime="5.55627914484"/>
		<edge id="23628728#0" traveltime="4.46753941033"/>
		<edge id="252385400" traveltime="1.28836199662"/>
		<edge id="23569963#0" traveltime="4.34837311346"/>
		<edge id="23569963#1" traveltime="1.1723534721"/>
		<edge id="23569963#2" traveltime="0.256301423119"/>
		<edge id="13858715" traveltime="5.69026023515"/>
		<edge id="27330495" traveltime="1.38497642539"/>
		<edge id="27330496" traveltime="0.869213682869"/>
		<edge id="27330497" traveltime="5.48917366998"/>
		<edge id="23572294#1" traveltime="16.3974515769"/>
		<edge id="23572294#0" traveltime="4.6492219681"/>
		<edge id="27330492" traveltime="11.6318961725"/>
		<edge id="23572294#2" traveltime="21.3922724819"/>
		<edge id="-25994511" traveltime="9.23128140287"/>
		<edge id="-25994517" traveltime="33.4230854859"/>
		<edge id="-25994515" traveltime="12.5077163649"/>
		<edge id="-25994519" traveltime="25.2404095353"/>
		<edge id="31741132" traveltime="28.1995516077"/>
		<edge id="-23947361#0" traveltime="3.79063396083"/>
		<edge id="-23947361#1" traveltime="15.4487879884"/>
		<edge id="-23947361#2" traveltime="1.70711192881"/>
		<edge id="365965544#1" traveltime="1.30597551035"/>
		<edge id="365965544#0" traveltime="3.09321090698"/>
		<edge id="365965544#3" traveltime="1.01625202727"/>
		<edge id="365965544#2" traveltime="3.23986963555"/>
		<edge id="339386971" traveltime="29.0349915167"/>
		<edge id="40856151" traveltime="1.97003342053"/>
		<edge id="25994328#4" traveltime="22.664955026"/>
		<edge id="40856159" traveltime="3.96026837766"/>
		<edge id="23570228#2" traveltime="4.60965357108"/>
		<edge id="-23841660" traveltime="0.0236085202281"/>
		<edge id="23570228#1" traveltime="10.8551750214"/>
		<edge id="23604118#2" traveltime="0.398472840354"/>
		<edge id="23604118#0" traveltime="24.6369490881"/>
		<edge id="23604118#1" traveltime="7.18613309385"/>
		<edge id="-24228800#2" traveltime="6.11381475491"/>
		<edge id="-32113742" traveltime="5.61906186646"/>
		<edge id="-32113741" traveltime="0.324540980365"/>
		<edge id="350046862" traveltime="5.01928325507"/>
		<edge id="350046866" traveltime="12.3059467572"/>
		<edge id="350046869" traveltime="1.51526239271"/>
		<edge id="350046868" traveltime="0.467391217634"/>
		<edge id="31520554" traveltime="0.38358983846"/>
		<edge id="31518750#0" traveltime="16.9688468519"/>
		<edge id="23689552#1" traveltime="2.72639375906"/>
		<edge id="23689552#0" traveltime="0.845064417774"/>
		<edge id="252667980#1" traveltime="0.79894094145"/>
		<edge id="252667980#0" traveltime="1.65051222371"/>
		<edge id="252667980#2" traveltime="1.63313427924"/>
		<edge id="46714797" traveltime="0.42414657778"/>
		<edge id="23785487#4" traveltime="12.3926737519"/>
		<edge id="-193664785" traveltime="1.62155392303"/>
		<edge id="27318140" traveltime="3.55122298133"/>
		<edge id="28108001#1" traveltime="2.38690660895"/>
		<edge id="28108001#0" traveltime="1.01188379828"/>
		<edge id="285676731" traveltime="9.010561184"/>
		<edge id="48044656" traveltime="22.4425369507"/>
		<edge id="243040742" traveltime="2.96546736055"/>
		<edge id="243040741" traveltime="0.618067683473"/>
		<edge id="243040740" traveltime="9.03506202883"/>
		<edge id="365781350" traveltime="1.99431411405"/>
		<edge id="365781356" traveltime="0.720543313192"/>
		<edge id="365781355" traveltime="5.29922324953"/>
		<edge id="365965549#0" traveltime="2.46293993707"/>
		<edge id="365965549#1" traveltime="1.1929431481"/>
		<edge id="365781359" traveltime="1.42420919826"/>
		<edge id="23802690#1" traveltime="0.367097420029"/>
		<edge id="23802690#0" traveltime="1.57923692117"/>
		<edge id="23802690#3" traveltime="0.187602260952"/>
		<edge id="23802690#2" traveltime="2.19419688093"/>
		<edge id="-453955195#0" traveltime="0.0149790712481"/>
		<edge id="9702304#4" traveltime="4.92202547663"/>
		<edge id="-23947375" traveltime="11.0937059044"/>
		<edge id="9702304#7" traveltime="2.70643128642"/>
		<edge id="372623525#1" traveltime="4.43696837022"/>
		<edge id="372623525#0" traveltime="11.3718463167"/>
		<edge id="9702304#6" traveltime="3.15227906393"/>
		<edge id="23570800#0" traveltime="14.0809975556"/>
		<edge id="23570800#1" traveltime="12.616606541"/>
		<edge id="34305140" traveltime="7.2353403641"/>
		<edge id="31952425#0" traveltime="17.9792471003"/>
		<edge id="31952425#1" traveltime="31.0874000095"/>
		<edge id="9702304#3" traveltime="11.2806516281"/>
		<edge id="9702304#2" traveltime="0.736213127969"/>
		<edge id="7990842" traveltime="11.3605516779"/>
		<edge id="7990841" traveltime="15.4923441042"/>
		<edge id="453471144" traveltime="0.0145939446628"/>
		<edge id="23763156#0" traveltime="3.38251953487"/>
		<edge id="23763156#1" traveltime="5.56476941119"/>
		<edge id="23763156#2" traveltime="1.25748015625"/>
		<edge id="350046863#4" traveltime="1.16596162431"/>
		<edge id="290451015" traveltime="1.39029234183"/>
		<edge id="-25995141#0" traveltime="1.49289054001"/>
		<edge id="290451017" traveltime="0.187221502106"/>
		<edge id="290451016" traveltime="13.2604545168"/>
		<edge id="-25995141#5" traveltime="2.00213166142"/>
		<edge id="-25995141#4" traveltime="60.388404822"/>
		<edge id="365787217" traveltime="4.23111469217"/>
		<edge id="31509572" traveltime="3.22263111002"/>
		<edge id="-23819116" traveltime="11.787677135"/>
		<edge id="365787218" traveltime="0.376679770608"/>
		<edge id="23785464#2" traveltime="2.53706016131"/>
		<edge id="8083534" traveltime="18.2363306635"/>
		<edge id="-23551884#3" traveltime="0.830333887154"/>
		<edge id="-23551884#2" traveltime="8.00405595021"/>
		<edge id="-23551884#1" traveltime="0.802506534097"/>
		<edge id="-23551884#0" traveltime="0.256502277738"/>
		<edge id="242254211#1" traveltime="1.06947397606"/>
		<edge id="242254211#0" traveltime="10.9667860444"/>
		<edge id="242254211#2" traveltime="1.52195664122"/>
		<edge id="179601808" traveltime="15.6164263157"/>
		<edge id="-25994509" traveltime="8.94803968906"/>
		<edge id="31510114" traveltime="3.74347503649"/>
		<edge id="31510116" traveltime="6.23174618676"/>
		<edge id="31510118" traveltime="3.22266018001"/>
		<edge id="188234548#2" traveltime="13.3405506994"/>
		<edge id="188234548#1" traveltime="0.443443369684"/>
		<edge id="188234548#0" traveltime="17.5287624293"/>
		<edge id="23568566#4" traveltime="4.61594868908"/>
		<edge id="32662617" traveltime="4.53677418483"/>
		<edge id="23689516#4" traveltime="15.7916363749"/>
		<edge id="23689516#3" traveltime="14.9068714323"/>
		<edge id="23689516#2" traveltime="23.6916031744"/>
		<edge id="23689516#1" traveltime="22.8386540907"/>
		<edge id="23689516#0" traveltime="18.358002814"/>
		<edge id="9702320" traveltime="9.34610450117"/>
		<edge id="9702322" traveltime="2.73093321844"/>
		<edge id="-23819685" traveltime="9.01936618689"/>
		<edge id="220958551" traveltime="1.7577076013"/>
		<edge id="220958550" traveltime="0.407229030289"/>
		<edge id="28262964" traveltime="0.96876809428"/>
		<edge id="28262963" traveltime="1.60301582822"/>
		<edge id="28262962" traveltime="10.7892029066"/>
		<edge id="32873314#0" traveltime="1.04446162689"/>
		<edge id="32873314#1" traveltime="14.3982366837"/>
		<edge id="365787225#2" traveltime="13.9793822985"/>
		<edge id="365787225#1" traveltime="12.3999531612"/>
		<edge id="365787225#0" traveltime="4.2049813137"/>
		<edge id="23947451" traveltime="16.0679413896"/>
		<edge id="27268906" traveltime="29.8724496157"/>
		<edge id="23590659#0" traveltime="1.8859040707"/>
		<edge id="23590659#1" traveltime="1.87450784955"/>
		<edge id="-23628728#2" traveltime="0.55100756073"/>
		<edge id="-23628728#1" traveltime="12.6401134377"/>
		<edge id="-23628728#0" traveltime="2.51563479982"/>
		<edge id="31516987#1" traveltime="0.149251320511"/>
		<edge id="31516987#0" traveltime="10.6180042455"/>
		<edge id="178451567#0" traveltime="56.7403996033"/>
		<edge id="178451567#1" traveltime="4.46398693228"/>
		<edge id="178451567#2" traveltime="10.6686727366"/>
		<edge id="350046871" traveltime="0.531159918618"/>
		<edge id="350046877" traveltime="1.29821788263"/>
		<edge id="350046874" traveltime="2.42136347837"/>
		<edge id="20616415" traveltime="16.9430978053"/>
		<edge id="350046878" traveltime="1.36321158322"/>
		<edge id="242254213" traveltime="0.717066348458"/>
		<edge id="365965548#1" traveltime="0.106533944517"/>
		<edge id="365965548#0" traveltime="9.64121797695"/>
		<edge id="365965548#2" traveltime="4.16229954058"/>
		<edge id="23785401" traveltime="1.83440016274"/>
		<edge id="23785404" traveltime="13.4643252771"/>
		<edge id="285676729" traveltime="2.22596549918"/>
		<edge id="358227399#0" traveltime="1.33834760225"/>
		<edge id="358227399#1" traveltime="4.63945315466"/>
		<edge id="40856458" traveltime="2.87981644038"/>
		<edge id="-25994328#3" traveltime="2.13524752749"/>
		<edge id="-25994328#2" traveltime="5.8050536697"/>
		<edge id="-25994328#1" traveltime="16.962800009"/>
		<edge id="-25994328#0" traveltime="1.64123896927"/>
		<edge id="-25994328#4" traveltime="23.0808540729"/>
		<edge id="-198862601" traveltime="3.40709961288"/>
		<edge id="365781347" traveltime="1.39815243499"/>
		<edge id="365781343" traveltime="0.718624150533"/>
		<edge id="-350046880" traveltime="1.08153398003"/>
		<edge id="365781348" traveltime="0.668535010922"/>
		<edge id="250683381" traveltime="8.31611261923"/>
		<edge id="-24260113#0" traveltime="7.80731155289"/>
		<edge id="-24260113#1" traveltime="4.28427375365"/>
		<edge id="358228120#1" traveltime="8.79378626815"/>
		<edge id="358228120#0" traveltime="2.80150763829"/>
		<edge id="7990838" traveltime="7.54611061873"/>
		<edge id="-23681466" traveltime="3.62878499225"/>
		<edge id="7990831" traveltime="17.6309986467"/>
		<edge id="395691388#0" traveltime="0.986091544612"/>
		<edge id="395691388#1" traveltime="11.6534239481"/>
		<edge id="-188234548#2" traveltime="6.65735112329"/>
		<edge id="-188234548#1" traveltime="1.43686565582"/>
		<edge id="-188234548#0" traveltime="8.80460943915"/>
		<edge id="24031616#0" traveltime="9.97201278335"/>
		<edge id="24031616#1" traveltime="0.810469493382"/>
		<edge id="32113742" traveltime="13.3891157558"/>
		<edge id="28119760#3" traveltime="0.716961443909"/>
		<edge id="-9702304#5" traveltime="6.42794025272"/>
		<edge id="23572251" traveltime="0.376315034157"/>
		<edge id="23785451#0" traveltime="0.289465175812"/>
		<edge id="23785451#1" traveltime="5.15807367703"/>
		<edge id="24260277#1" traveltime="14.3863340677"/>
		<edge id="24260277#0" traveltime="0.299344182315"/>
		<edge id="24260277#2" traveltime="18.4474229406"/>
		<edge id="253117358" traveltime="3.66004040802"/>
		<edge id="253117359" traveltime="9.09133603882"/>
		<edge id="-9702304#6" traveltime="1.92408956706"/>
		<edge id="-9702386#2" traveltime="11.6189276604"/>
		<edge id="-9702386#1" traveltime="1.16046478768"/>
		<edge id="-9702386#0" traveltime="6.41977672483"/>
		<edge id="253117356" traveltime="4.82414582151"/>
		<edge id="253117357" traveltime="33.0481795072"/>
		<edge id="23818206" traveltime="2.35443848522"/>
		<edge id="23604035#1" traveltime="2.95527682279"/>
		<edge id="-23570228#2" traveltime="6.31960976412"/>
		<edge id="-23570228#0" traveltime="3.84280102516"/>
		<edge id="-23570228#1" traveltime="14.6524469437"/>
		<edge id="179601813" traveltime="9.41285740638"/>
		<edge id="179921326" traveltime="2.34679644562"/>
		<edge id="23838548" traveltime="7.76029437492"/>
		<edge id="23818110" traveltime="14.0789715122"/>
		<edge id="4085417" traveltime="0.801071431182"/>
		<edge id="4085416" traveltime="14.155868445"/>
		<edge id="4085414" traveltime="21.10373154"/>
		<edge id="-220958549#4" traveltime="1.09158657639"/>
		<edge id="-220958549#5" traveltime="8.15308567124"/>
		<edge id="-220958549#6" traveltime="11.760810398"/>
		<edge id="-220958549#0" traveltime="14.6335390814"/>
		<edge id="-220958549#1" traveltime="15.5932161892"/>
		<edge id="-220958549#2" traveltime="6.24515109725"/>
		<edge id="-220958549#3" traveltime="11.621393432"/>
		<edge id="31516860#1" traveltime="0.364986253973"/>
		<edge id="31516860#0" traveltime="3.78908959502"/>
		<edge id="-23570208" traveltime="2.26585994187"/>
		<edge id="198862601" traveltime="3.91694061523"/>
		<edge id="198862600" traveltime="43.3715664111"/>
		<edge id="198862603" traveltime="21.6458601696"/>
		<edge id="198862602" traveltime="8.80437785159"/>
		<edge id="198862606" traveltime="21.793452164"/>
		<edge id="198862609" traveltime="2.88492705229"/>
		<edge id="198862608" traveltime="18.175668923"/>
		<edge id="31516986#0" traveltime="1.04457682623"/>
		<edge id="31516986#1" traveltime="0.0399787247773"/>
		<edge id="220958543" traveltime="0.792359270641"/>
		<edge id="96806878" traveltime="5.29444551949"/>
		<edge id="220958541" traveltime="41.1027057187"/>
		<edge id="220958547" traveltime="0.956638564704"/>
		<edge id="220958544" traveltime="1.80043885696"/>
		<edge id="220958545" traveltime="5.67968023725"/>
		<edge id="-23569963#0" traveltime="3.23494697694"/>
		<edge id="-23569963#1" traveltime="0.788480472148"/>
		<edge id="-23569963#2" traveltime="0.318547710147"/>
		<edge id="27268914" traveltime="4.39162535712"/>
		<edge id="444135402" traveltime="12.6446671259"/>
		<edge id="27268910" traveltime="17.3289268648"/>
		<edge id="243040717#0" traveltime="0.238665179155"/>
		<edge id="198862591" traveltime="39.1676130564"/>
		<edge id="198862593" traveltime="20.7297600942"/>
		<edge id="198862598" traveltime="5.55681531077"/>
		<edge id="243040718#3" traveltime="6.08885295144"/>
		<edge id="243040718#2" traveltime="0.0685033850608"/>
		<edge id="243040718#1" traveltime="1.41264063035"/>
		<edge id="243040718#0" traveltime="2.47775976602"/>
		<edge id="243040718#5" traveltime="1.05289148609"/>
		<edge id="243040718#4" traveltime="7.4221191559"/>
		<edge id="365787219#0" traveltime="5.71462186372"/>
		<edge id="365787219#1" traveltime="6.34518352826"/>
		<edge id="349660584" traveltime="6.13626184309"/>
		<edge id="23570763#0" traveltime="3.42482446204"/>
		<edge id="23570763#1" traveltime="7.31477987318"/>
		<edge id="23570763#2" traveltime="9.29154935419"/>
		<edge id="23570763#3" traveltime="0.970359221042"/>
		<edge id="23570417#18" traveltime="4.61060647089"/>
		<edge id="23570417#19" traveltime="18.4638631309"/>
		<edge id="23570417#14" traveltime="4.47173507886"/>
		<edge id="23570417#15" traveltime="12.0961189517"/>
		<edge id="23570417#16" traveltime="0.79478987412"/>
		<edge id="23570417#17" traveltime="1.24391237982"/>
		<edge id="23570417#10" traveltime="0.482950753172"/>
		<edge id="23570417#11" traveltime="2.06130522373"/>
		<edge id="23570417#12" traveltime="9.92978912229"/>
		<edge id="23570417#13" traveltime="0.120602921778"/>
		<edge id="365965546#1" traveltime="11.3265368621"/>
		<edge id="-27602147" traveltime="0.823863393349"/>
		<edge id="365965546#0" traveltime="13.4018264637"/>
		<edge id="23785439" traveltime="12.4929908275"/>
		<edge id="365965547#2" traveltime="0.722244583198"/>
		<edge id="365965547#3" traveltime="17.1655160496"/>
		<edge id="365965547#0" traveltime="3.49488014414"/>
		<edge id="365965547#1" traveltime="14.2000031351"/>
		<edge id="365965547#4" traveltime="1.22319093544"/>
		<edge id="27397710" traveltime="0.015704584134"/>
		<edge id="27397711" traveltime="0.480625111583"/>
		<edge id="31520557#3" traveltime="6.59342612311"/>
		<edge id="31520557#2" traveltime="1.75564823732"/>
		<edge id="31520557#1" traveltime="0.238347821144"/>
		<edge id="31520557#0" traveltime="0.338419035897"/>
		<edge id="243040735#0" traveltime="6.2550048567"/>
		<edge id="-24031683#1" traveltime="13.441386471"/>
		<edge id="-24031683#2" traveltime="3.37305067465"/>
		<edge id="23785464#1" traveltime="8.28788209704"/>
		<edge id="28108002#0" traveltime="2.09775343641"/>
		<edge id="28108002#1" traveltime="3.98408976135"/>
		<edge id="28108002#2" traveltime="12.9166589367"/>
		<edge id="395691389#1" traveltime="0.432177270397"/>
		<edge id="395691389#0" traveltime="7.37950191788"/>
		<edge id="395691389#2" traveltime="0.677230938826"/>
		<edge id="242254209" traveltime="0.47079904201"/>
		<edge id="31983270" traveltime="0.170480422692"/>
		<edge id="46832782#0" traveltime="0.689069252762"/>
		<edge id="33168034#1" traveltime="15.7934014101"/>
		<edge id="34778563#1" traveltime="3.60065543686"/>
		<edge id="7990824" traveltime="8.42582730256"/>
		<edge id="7990827" traveltime="42.4299530974"/>
		<edge id="258339606" traveltime="0.62637042699"/>
		<edge id="350046857#0" traveltime="3.81424007016"/>
		<edge id="365756276#4" traveltime="1.40368390155"/>
		<edge id="350046857#2" traveltime="14.8082186791"/>
		<edge id="365756276#1" traveltime="0.122028228888"/>
		<edge id="365756276#0" traveltime="2.68954885416"/>
		<edge id="31518748#0" traveltime="1.67392438711"/>
		<edge id="365756276#2" traveltime="2.33040758703"/>
		<edge id="23569730" traveltime="7.61849706539"/>
		<edge id="80347011" traveltime="3.0790339717"/>
		<edge id="23947361#0" traveltime="16.8228267339"/>
		<edge id="23947361#1" traveltime="14.263436161"/>
		<edge id="23947361#2" traveltime="1.51330446519"/>
		<edge id="31510115#2" traveltime="0.813029460283"/>
		<edge id="31510115#0" traveltime="0.208000451145"/>
		<edge id="31510115#1" traveltime="5.50709490717"/>
		<edge id="31540505#4" traveltime="0.50159492618"/>
		<edge id="-23785499#0" traveltime="13.5382352132"/>
		<edge id="-23785499#1" traveltime="5.29924053048"/>
		<edge id="31540505#0" traveltime="5.38908086151"/>
		<edge id="31540505#1" traveltime="0.958935458325"/>
		<edge id="31540505#2" traveltime="0.0135657434698"/>
		<edge id="31540505#3" traveltime="16.0596590064"/>
		<edge id="-24228720#4" traveltime="7.18885308855"/>
		<edge id="-24228720#5" traveltime="12.3691243922"/>
		<edge id="-24228720#6" traveltime="10.3796286891"/>
		<edge id="-24228720#7" traveltime="8.92168691467"/>
		<edge id="-24228720#0" traveltime="15.047411882"/>
		<edge id="-24228720#1" traveltime="12.278678593"/>
		<edge id="-24228720#2" traveltime="0.703976097383"/>
		<edge id="-24228720#3" traveltime="0.901887405462"/>
		<edge id="31983269#0" traveltime="10.8244934925"/>
		<edge id="31983269#1" traveltime="0.775275383095"/>
		<edge id="-24228720#8" traveltime="0.505951197817"/>
		<edge id="-24228720#9" traveltime="8.53091614372"/>
		<edge id="342175899#2" traveltime="3.42581716341"/>
		<edge id="342175899#3" traveltime="3.27853789336"/>
		<edge id="342175899#0" traveltime="1.60492091925"/>
		<edge id="342175899#1" traveltime="0.708334655905"/>
		<edge id="365787227#1" traveltime="0.407194229297"/>
		<edge id="365787227#0" traveltime="5.50727800929"/>
		<edge id="243040712#1" traveltime="10.4110896136"/>
		<edge id="243040712#0" traveltime="0.0230629060929"/>
		<edge id="220958542#3" traveltime="3.76312248972"/>
		<edge id="220958542#2" traveltime="7.71098749954"/>
		<edge id="220958542#1" traveltime="2.18946780683"/>
		<edge id="220958542#0" traveltime="0.107512677601"/>
		<edge id="220958542#6" traveltime="10.9432751463"/>
		<edge id="220958542#5" traveltime="1.74328837489"/>
		<edge id="220958542#4" traveltime="5.39381671339"/>
		<edge id="31952422" traveltime="7.75097899657"/>
		<edge id="31952423" traveltime="22.6043479843"/>
		<edge id="31952421" traveltime="8.66461491228"/>
		<edge id="31952426" traveltime="15.5505348107"/>
		<edge id="31952427" traveltime="4.91206931761"/>
		<edge id="31952424" traveltime="7.20548506595"/>
		<edge id="31952428" traveltime="2.96149734136"/>
		<edge id="-455252241" traveltime="6.15679804075"/>
		<edge id="45340031#3" traveltime="4.25610920892"/>
		<edge id="45340031#2" traveltime="18.0436352875"/>
		<edge id="45340031#1" traveltime="0.14000602573"/>
		<edge id="45340031#0" traveltime="3.78305956835"/>
		<edge id="-443564911" traveltime="0.0141756546723"/>
		<edge id="-45340032" traveltime="13.2357171601"/>
		<edge id="23785487#5" traveltime="13.8694465048"/>
		<edge id="23569642#4" traveltime="2.34453027838"/>
		<edge id="198862613" traveltime="28.7254426948"/>
		<edge id="198862611" traveltime="14.572064268"/>
		<edge id="198862616" traveltime="0.314596481366"/>
		<edge id="23569642#1" traveltime="4.45727279996"/>
		<edge id="23569642#2" traveltime="5.52842730024"/>
		<edge id="23569642#3" traveltime="5.47648599242"/>
		<edge id="198862618" traveltime="3.08597287689"/>
		<edge id="198862619" traveltime="7.62728363114"/>
		<edge id="27268913#1" traveltime="5.82769453297"/>
		<edge id="27268913#0" traveltime="10.88660674"/>
		<edge id="23695586#5" traveltime="18.0045815557"/>
		<edge id="23695586#4" traveltime="0.463079438549"/>
		<edge id="23695586#7" traveltime="8.13818530803"/>
		<edge id="23695586#6" traveltime="9.10484644972"/>
		<edge id="23695586#1" traveltime="5.34242767994"/>
		<edge id="23695586#0" traveltime="0.164909319522"/>
		<edge id="23695586#3" traveltime="0.607774006527"/>
		<edge id="23695586#2" traveltime="14.4592042464"/>
		<edge id="23695586#8" traveltime="0.29375681135"/>
		<edge id="-23818365#1" traveltime="4.88460690468"/>
		<edge id="-23818365#0" traveltime="10.5643757631"/>
		<edge id="258244174#1" traveltime="8.19376381525"/>
		<edge id="258244174#0" traveltime="0.785993435494"/>
		<edge id="258244174#2" traveltime="0.147486920599"/>
		<edge id="-23802586#2" traveltime="0.311530595444"/>
		<edge id="-23802586#1" traveltime="11.7303411327"/>
		<edge id="-23802586#0" traveltime="0.769279811208"/>
		<edge id="31516177" traveltime="0.208172080988"/>
		<edge id="457487645" traveltime="1.4981525581"/>
		<edge id="24014142" traveltime="0.326256458338"/>
		<edge id="90282207#1" traveltime="2.79815038664"/>
		<edge id="31520295" traveltime="7.84426057391"/>
		<edge id="31520296" traveltime="3.10583212096"/>
		<edge id="90282207#2" traveltime="2.04831098682"/>
		<edge id="23802803" traveltime="4.29346646108"/>
		<edge id="23570417#21" traveltime="0.227079184331"/>
		<edge id="23570417#20" traveltime="1.50626480914"/>
		<edge id="23570417#22" traveltime="2.8033435107"/>
		<edge id="395691387" traveltime="1.57740698721"/>
		<edge id="23785519#3" traveltime="6.28512147504"/>
		<edge id="23785519#2" traveltime="3.01386118752"/>
		<edge id="23785519#1" traveltime="5.88296146591"/>
		<edge id="23785519#0" traveltime="27.6949446936"/>
		<edge id="45547150#2" traveltime="0.967210018791"/>
		<edge id="403906245#1" traveltime="0.740503399496"/>
		<edge id="403906245#0" traveltime="3.42886607197"/>
		<edge id="23689459#5" traveltime="7.83998309819"/>
		<edge id="23689459#4" traveltime="4.11044746237"/>
		<edge id="23689459#1" traveltime="2.10044897786"/>
		<edge id="23689459#0" traveltime="0.799417605848"/>
		<edge id="23689459#3" traveltime="7.70887924387"/>
		<edge id="23689459#2" traveltime="20.720832956"/>
		<edge id="350046853" traveltime="5.55497204203"/>
		<edge id="350046855" traveltime="0.20227340969"/>
		<edge id="23785477#0" traveltime="7.82781912129"/>
		<edge id="23785477#1" traveltime="22.3521219508"/>
		<edge id="27397709" traveltime="1.30323452473"/>
		<edge id="261058031#2" traveltime="3.44976788196"/>
		<edge id="261058031#3" traveltime="0.348516276111"/>
		<edge id="261058031#0" traveltime="17.3348577348"/>
		<edge id="365756266" traveltime="3.00425790056"/>
		<edge id="31516988" traveltime="0.858334198061"/>
		<edge id="215446160#2" traveltime="1.6663993974"/>
		<edge id="215446160#1" traveltime="5.70858324388"/>
		<edge id="215446160#0" traveltime="5.50235839724"/>
		<edge id="7990815" traveltime="78.9813322876"/>
		<edge id="7990814" traveltime="21.8475177619"/>
		<edge id="-23695586#8" traveltime="0.1827675278"/>
		<edge id="23818365#1" traveltime="10.6748432153"/>
		<edge id="23818365#0" traveltime="8.93714998668"/>
		<edge id="-23695586#5" traveltime="14.3138236288"/>
		<edge id="-23695586#4" traveltime="0.553451160856"/>
		<edge id="-23695586#7" traveltime="7.91132065538"/>
		<edge id="-23695586#6" traveltime="7.94100698281"/>
		<edge id="-23695586#1" traveltime="10.5849170847"/>
		<edge id="-23695586#0" traveltime="0.812012612069"/>
		<edge id="-23695586#3" traveltime="1.00413815963"/>
		<edge id="-23695586#2" traveltime="8.51153841211"/>
		<edge id="24031615#1" traveltime="3.45613153368"/>
		<edge id="32038118#0" traveltime="16.4037502921"/>
		<edge id="350046863#7" traveltime="1.4378238864"/>
		<edge id="-23947367#2" traveltime="9.980577244"/>
		<edge id="-23947367#3" traveltime="2.27005551894"/>
		<edge id="-23947367#0" traveltime="11.9926060989"/>
		<edge id="350046863#6" traveltime="19.2368854248"/>
		<edge id="45547151" traveltime="0.120058024391"/>
		<edge id="-443977183#6" traveltime="0.597009593215"/>
		<edge id="217904135" traveltime="0.503910927264"/>
		<edge id="217904136" traveltime="1.74136329262"/>
		<edge id="23590984" traveltime="2.97361818463"/>
		<edge id="90282245" traveltime="2.86663030329"/>
		<edge id="90282246" traveltime="2.20930680037"/>
		<edge id="90282241" traveltime="0.714350716098"/>
		<edge id="243040715#2" traveltime="4.47930797636"/>
		<edge id="243040715#0" traveltime="0.817230915356"/>
		<edge id="243040715#1" traveltime="0.0504442718121"/>
		<edge id="31510029#2" traveltime="1.38388587828"/>
		<edge id="31510029#0" traveltime="45.8181608692"/>
		<edge id="31510029#1" traveltime="1.53869715812"/>
		<edge id="-443977183#4" traveltime="1.2543037791"/>
		<edge id="23570228#0" traveltime="4.1024730891"/>
		<edge id="32038118#1" traveltime="3.04969994232"/>
		<edge id="23570799#1" traveltime="22.8057831342"/>
		<edge id="23570799#0" traveltime="19.3999290868"/>
		<edge id="48098911" traveltime="9.78341495954"/>
		<edge id="-445309968#1" traveltime="19.9608341421"/>
		<edge id="23689375" traveltime="44.8800225237"/>
		<edge id="23785416#1" traveltime="2.22073894636"/>
		<edge id="23785416#0" traveltime="1.33699784015"/>
		<edge id="32113734#1" traveltime="4.37360248388"/>
		<edge id="32113734#0" traveltime="13.0072320481"/>
		<edge id="454571999" traveltime="1.88893644904"/>
		<edge id="31952431" traveltime="5.45672174591"/>
		<edge id="-24031683#0" traveltime="0.328122766197"/>
		<edge id="243040735#1" traveltime="0.275474426611"/>
		<edge id="23785464#0" traveltime="3.11526676763"/>
		<edge id="198862627" traveltime="6.87020598761"/>
		<edge id="198862626" traveltime="2.0144050088"/>
		<edge id="198862625" traveltime="8.02167382116"/>
		<edge id="198862620" traveltime="5.43690431418"/>
		<edge id="23785502#1" traveltime="18.6256202818"/>
		<edge id="23785502#0" traveltime="6.08141959377"/>
		<edge id="198862629" traveltime="2.40074468547"/>
		<edge id="198862628" traveltime="6.53425542216"/>
		<edge id="9702386#2" traveltime="16.7592317201"/>
		<edge id="96806892" traveltime="30.6654971519"/>
		<edge id="96806893" traveltime="1.93203580334"/>
		<edge id="96806894" traveltime="0.982105700793"/>
		<edge id="-23551886" traveltime="8.22381184211"/>
		<edge id="361775197#10" traveltime="3.10295693346"/>
		<edge id="361775197#11" traveltime="10.8556831433"/>
		<edge id="361775197#12" traveltime="0.801504081759"/>
		<edge id="-453471144" traveltime="0.0278619140487"/>
		<edge id="-32873313" traveltime="17.4239409956"/>
		<edge id="31952219" traveltime="16.7681211054"/>
		<edge id="31952218" traveltime="9.91767341788"/>
		<edge id="-9702320" traveltime="13.3550820519"/>
		<edge id="25994328#3" traveltime="1.9965562326"/>
		<edge id="25994328#2" traveltime="4.94617793215"/>
		<edge id="25994328#1" traveltime="10.7465221053"/>
		<edge id="25994328#0" traveltime="2.95892805247"/>
		<edge id="31520710#2" traveltime="1.60217060118"/>
		<edge id="31520710#3" traveltime="2.29635243626"/>
		<edge id="31520710#0" traveltime="1.49354478857"/>
		<edge id="31520710#1" traveltime="0.407447933053"/>
		<edge id="23802696#2" traveltime="1.41054739796"/>
		<edge id="23802696#1" traveltime="23.4928568107"/>
		<edge id="23802696#0" traveltime="1.52276888786"/>
		<edge id="31518750#1" traveltime="22.2900699323"/>
		<edge id="23570218#1" traveltime="0.438014280671"/>
		<edge id="31518750#3" traveltime="0.73639808839"/>
		<edge id="31518750#2" traveltime="0.300460651518"/>
		<edge id="23570218#0" traveltime="8.7184743927"/>
		<edge id="257657829" traveltime="0.839367485783"/>
		<edge id="395691398" traveltime="3.08361277001"/>
		<edge id="9702304#8" traveltime="3.87360730277"/>
		<edge id="395691390" traveltime="10.8426263414"/>
		<edge id="395691391" traveltime="5.38216537605"/>
		<edge id="395691392" traveltime="4.84012526181"/>
		<edge id="395691393" traveltime="1.43176052016"/>
		<edge id="9702304#1" traveltime="11.4748198193"/>
		<edge id="9702304#0" traveltime="2.24807633232"/>
		<edge id="395691396" traveltime="17.5089155301"/>
		<edge id="395691397" traveltime="0.387336985329"/>
		<edge id="-23785477#0" traveltime="13.8801041719"/>
		<edge id="-23785477#1" traveltime="11.7789241942"/>
		<edge id="27882348" traveltime="8.82413550887"/>
		<edge id="-324330499" traveltime="4.32420001357"/>
		<edge id="23763167#0" traveltime="2.74996670148"/>
		<edge id="23763167#1" traveltime="0.869342731796"/>
		<edge id="23763167#2" traveltime="0.853488228258"/>
		<edge id="46714372#1" traveltime="1.674712937"/>
		<edge id="46714372#0" traveltime="0.0171898088915"/>
		<edge id="24228720#10" traveltime="8.94359578238"/>
		<edge id="24228720#11" traveltime="0.717916259302"/>
		<edge id="8085554" traveltime="44.2223997878"/>
		<edge id="257662110" traveltime="27.3658996082"/>
		<edge id="28119760#8" traveltime="1.82417692686"/>
		<edge id="28119760#1" traveltime="6.84234929241"/>
		<edge id="28119760#0" traveltime="1.89685349017"/>
		<edge id="32113741" traveltime="0.0587210663676"/>
		<edge id="28119760#2" traveltime="11.7408995877"/>
		<edge id="28119760#5" traveltime="22.7440128579"/>
		<edge id="28119760#4" traveltime="0.89663892234"/>
		<edge id="28119760#7" traveltime="0.327979913079"/>
		<edge id="28119760#6" traveltime="5.99965313921"/>
		<edge id="-449732383" traveltime="73.9922204958"/>
		<edge id="-449732385" traveltime="3.16053217025"/>
		<edge id="-449732384" traveltime="3.62240719955"/>
		<edge id="34778398#0" traveltime="11.430222938"/>
		<edge id="34778398#1" traveltime="2.00139946508"/>
		<edge id="34778398#2" traveltime="4.81524448007"/>
		<edge id="34778398#3" traveltime="1.24623846569"/>
		<edge id="34778563#0" traveltime="4.17392551222"/>
		<edge id="33168034#0" traveltime="14.0206301128"/>
		<edge id="23590621" traveltime="1.11395121169"/>
		<edge id="23551880" traveltime="17.9562886941"/>
		<edge id="23551886" traveltime="7.98616666367"/>
		<edge id="-103630528" traveltime="7.98488823885"/>
		<edge id="215446159" traveltime="12.8075874242"/>
		<edge id="32038115" traveltime="0.279504561659"/>
		<edge id="31518747" traveltime="0.228087951268"/>
		<edge id="-23818110" traveltime="29.8143536249"/>
		<edge id="24228288" traveltime="3.94011663051"/>
		<edge id="24228289" traveltime="1.3412234687"/>
		<edge id="23590790#0" traveltime="30.0342732378"/>
		<edge id="23590790#1" traveltime="8.80894228074"/>
		<edge id="23590790#2" traveltime="32.984881946"/>
		<edge id="32038119" traveltime="0.373297444256"/>
		<edge id="23591004" traveltime="7.91847113286"/>
		<edge id="23591006" traveltime="7.90618369022"/>
		<edge id="23591007" traveltime="10.0151031713"/>
		<edge id="23568752#1" traveltime="5.10060134213"/>
		<edge id="23568752#0" traveltime="1.54050867363"/>
		<edge id="48290325#0" traveltime="82.9602348706"/>
		<edge id="48290325#1" traveltime="11.4995117848"/>
		<edge id="48290325#2" traveltime="1.91563576964"/>
		<edge id="48290325#3" traveltime="12.0998118922"/>
		<edge id="23569688" traveltime="2.7017415082"/>
		<edge id="23569686" traveltime="5.62803763758"/>
		<edge id="23689562" traveltime="12.2371623923"/>
		<edge id="23689561" traveltime="9.81248622429"/>
		<edge id="27602147" traveltime="0.728757117633"/>
		<edge id="361775195" traveltime="3.98670489867"/>
		<edge id="23590997" traveltime="4.48374328274"/>
		<edge id="22278675" traveltime="1.6736549851"/>
		<edge id="24031615#4" traveltime="1.49783949619"/>
		<edge id="350046857#1" traveltime="20.0941505106"/>
		<edge id="-23912456" traveltime="16.6960167266"/>
		<edge id="23570850" traveltime="16.0674156465"/>
		<edge id="28258517" traveltime="4.20785942895"/>
		<edge id="365756276#3" traveltime="3.66180366421"/>
		<edge id="31518748#1" traveltime="0.09710326725"/>
		<edge id="251271720" traveltime="2.69984014116"/>
		<edge id="251271721" traveltime="2.8349186844"/>
		<edge id="24252065#2" traveltime="20.3448551124"/>
		<edge id="24252065#1" traveltime="11.4873618907"/>
		<edge id="24252065#0" traveltime="0.171272028496"/>
		<edge id="96806886" traveltime="18.4978515267"/>
		<edge id="324330498#0" traveltime="6.22167096424"/>
		<edge id="324330498#1" traveltime="4.97393525693"/>
		<edge id="23785475#0" traveltime="10.0008855241"/>
		<edge id="23785475#1" traveltime="22.0206729995"/>
		<edge id="46714457" traveltime="0.741037161502"/>
		<edge id="45340032" traveltime="17.3406600303"/>
		<edge id="361775197#2" traveltime="2.50898424939"/>
		<edge id="361775197#3" traveltime="3.26726687014"/>
		<edge id="361775197#0" traveltime="2.06480004559"/>
		<edge id="361775197#1" traveltime="1.49570777663"/>
		<edge id="361775197#6" traveltime="8.54674308793"/>
		<edge id="361775197#7" traveltime="4.41328950338"/>
		<edge id="361775197#4" traveltime="10.3817483682"/>
		<edge id="361775197#5" traveltime="0.0930195506156"/>
		<edge id="361775197#8" traveltime="14.3578668851"/>
		<edge id="361775197#9" traveltime="13.7414902039"/>
		<edge id="23947381" traveltime="3.90230363602"/>
		<edge id="23785399#1" traveltime="7.87128233041"/>
		<edge id="23785399#0" traveltime="8.57045569257"/>
		<edge id="23785399#2" traveltime="2.30601038112"/>
		<edge id="198862630" traveltime="6.44865525153"/>
		<edge id="365782826#4" traveltime="0.465314705069"/>
		<edge id="198862633" traveltime="4.16472197308"/>
		<edge id="198862634" traveltime="37.7838377762"/>
		<edge id="198862635" traveltime="22.7397438404"/>
		<edge id="365782826#3" traveltime="12.6388727463"/>
		<edge id="365782826#2" traveltime="8.87242390478"/>
		<edge id="217904133" traveltime="0.810271539528"/>
		<edge id="23947367#2" traveltime="12.602595935"/>
		<edge id="23947367#3" traveltime="2.53024472984"/>
		<edge id="23947367#0" traveltime="13.3237832843"/>
		<edge id="23947367#1" traveltime="0.850732012524"/>
		<edge id="459587081#3" traveltime="7.47310702914"/>
		<edge id="459587081#2" traveltime="1.60861249413"/>
		<edge id="459587081#1" traveltime="0.290588017335"/>
		<edge id="459587081#0" traveltime="18.4157021288"/>
		<edge id="31509618#2" traveltime="1.32832352303"/>
		<edge id="31509618#3" traveltime="5.87540777668"/>
		<edge id="31509618#0" traveltime="2.08910385892"/>
		<edge id="31509618#1" traveltime="5.98833612318"/>
		<edge id="23785440" traveltime="10.7918667307"/>
		<edge id="243046551" traveltime="0.0149686739329"/>
		<edge id="-23785502#1" traveltime="8.90786570343"/>
		<edge id="-23785502#0" traveltime="5.40666289363"/>
		<edge id="28119759#1" traveltime="5.56855992256"/>
		<edge id="28119759#0" traveltime="0.552253171291"/>
		<edge id="97405322" traveltime="8.72420751884"/>
		<edge id="243040733#0" traveltime="1.12786720914"/>
		<edge id="243040733#1" traveltime="1.95605152469"/>
		<edge id="23681482#1" traveltime="0.255074264461"/>
		<edge id="23681482#0" traveltime="12.0007939793"/>
		<edge id="23681482#2" traveltime="3.85696464209"/>
		<edge id="-31741033" traveltime="36.2189906404"/>
		<edge id="31519922#1" traveltime="0.13366130972"/>
		<edge id="-31741034" traveltime="7.36465054627"/>
		<edge id="243040723#1" traveltime="7.77325168465"/>
		<edge id="243040723#0" traveltime="9.9636878225"/>
		<edge id="243040723#2" traveltime="0.499278355155"/>
		<edge id="33168033" traveltime="6.54460218098"/>
		<edge id="-20616415" traveltime="8.38195120875"/>
		<edge id="403906248" traveltime="4.15708159636"/>
		<edge id="25994523#1" traveltime="22.5300076355"/>
		<edge id="23763154#0" traveltime="0.191703940307"/>
		<edge id="23763154#1" traveltime="2.39770957559"/>
		<edge id="-23569944" traveltime="3.73887533216"/>
		<edge id="23912456" traveltime="15.0489650119"/>
		<edge id="365756275" traveltime="2.64848222768"/>
		<edge id="-465130863" traveltime="5.72614444058"/>
		<edge id="220958546#2" traveltime="0.478049929924"/>
		<edge id="220958546#1" traveltime="1.08552492498"/>
		<edge id="220958546#0" traveltime="0.717913393457"/>
		<edge id="365965541#0" traveltime="31.9316973924"/>
		<edge id="365965541#1" traveltime="0.568315445361"/>
		<edge id="365965541#2" traveltime="0.0108406875792"/>
		<edge id="372623526#0" traveltime="7.02652861522"/>
		<edge id="372623526#1" traveltime="7.93473155725"/>
		<edge id="27269040" traveltime="14.815377855"/>
		<edge id="-23570103#0" traveltime="7.44814643584"/>
		<edge id="31516861#0" traveltime="3.2641503207"/>
		<edge id="24252393#1" traveltime="0.459668031412"/>
		<edge id="24252393#0" traveltime="3.25373478273"/>
		<edge id="31516861#1" traveltime="0.102150834593"/>
		<edge id="-31778240" traveltime="0.128024314995"/>
		<edge id="23695575#4" traveltime="0.976790806839"/>
		<edge id="23695575#3" traveltime="6.30308039269"/>
		<edge id="23695575#2" traveltime="9.96344215495"/>
		<edge id="23695575#1" traveltime="1.28962756256"/>
		<edge id="23695575#0" traveltime="0.383587130233"/>
		<edge id="26768443" traveltime="12.4447214319"/>
		<edge id="365782826#1" traveltime="11.1183732544"/>
		<edge id="23802565#4" traveltime="0.706294124124"/>
		<edge id="23802565#5" traveltime="11.1095955906"/>
		<edge id="23802565#2" traveltime="9.13303851544"/>
		<edge id="23802565#3" traveltime="14.5576754246"/>
		<edge id="23802565#0" traveltime="1.74967029278"/>
		<edge id="23802565#1" traveltime="7.98809024343"/>
		<edge id="-435219533#5" traveltime="7.80315747561"/>
		<edge id="-435219533#4" traveltime="4.53469165613"/>
		<edge id="-435219533#1" traveltime="0.638800608864"/>
		<edge id="-435219533#0" traveltime="10.5018683659"/>
		<edge id="-435219533#3" traveltime="8.616375897"/>
		<edge id="-435219533#2" traveltime="4.21148927521"/>
		<edge id="-100682788" traveltime="3.73962841808"/>
		<edge id="90282216#2" traveltime="2.31586597219"/>
		<edge id="23785500" traveltime="10.8192648342"/>
		<edge id="162845079" traveltime="0.268916311156"/>
		<edge id="32663583" traveltime="15.4270008849"/>
		<edge id="-23551883#0" traveltime="11.5698084986"/>
		<edge id="-23551883#1" traveltime="15.0614715615"/>
		<edge id="-23590637#0" traveltime="30.6083955358"/>
		<edge id="-23590637#1" traveltime="40.7742279487"/>
		<edge id="23551877#4" traveltime="14.3109687051"/>
		<edge id="23551877#1" traveltime="1.23190059724"/>
		<edge id="23551877#0" traveltime="0.0208949224634"/>
		<edge id="23551877#3" traveltime="5.3740966331"/>
		<edge id="23551877#2" traveltime="0.197982478127"/>
		<edge id="25994326#1" traveltime="16.2428644495"/>
		<edge id="25994326#0" traveltime="1.53697002149"/>
		<edge id="23785472" traveltime="10.2060085118"/>
		<edge id="465130863" traveltime="4.41377706861"/>
		<edge id="-23912440" traveltime="17.8088419715"/>
		<edge id="-23947358#0" traveltime="14.6252618431"/>
		<edge id="-23947358#1" traveltime="22.1939008068"/>
		<edge id="9702512" traveltime="1.44760147146"/>
		<edge id="9702511" traveltime="0.635498111237"/>
		<edge id="9702516" traveltime="1.35536419568"/>
		<edge id="9702514" traveltime="1.19845204383"/>
		<edge id="365787231#0" traveltime="0.275987013684"/>
		<edge id="365787231#1" traveltime="24.5301955912"/>
		<edge id="365787231#2" traveltime="0.762656242935"/>
		<edge id="365787231#3" traveltime="14.9009475404"/>
		<edge id="365787231#4" traveltime="7.93184423036"/>
		<edge id="365787231#5" traveltime="9.47093908862"/>
		<edge id="365787231#6" traveltime="5.27707157851"/>
		<edge id="25025342" traveltime="1.30347681786"/>
		<edge id="-28108002#0" traveltime="2.26655110319"/>
		<edge id="-28108002#1" traveltime="5.30546411379"/>
		<edge id="-28108002#2" traveltime="10.8298008225"/>
		<edge id="103630528" traveltime="6.72930807259"/>
		<edge id="243040724#0" traveltime="1.6095015472"/>
		<edge id="243040724#1" traveltime="0.0999837256624"/>
		<edge id="23590637#0" traveltime="22.6348386155"/>
		<edge id="23590637#1" traveltime="49.228457358"/>
		<edge id="-22278675" traveltime="0.918351505341"/>
		<edge id="-27330492" traveltime="10.924723863"/>
		<edge id="-24228800#1" traveltime="3.62196650891"/>
		<edge id="-24228800#0" traveltime="19.9694420127"/>
		<edge id="-27330497" traveltime="5.15857816685"/>
		<edge id="20617535#2" traveltime="0.628059277718"/>
		<edge id="23841670#2" traveltime="26.740439476"/>
		<edge id="20617535#0" traveltime="1.26929961425"/>
		<edge id="20617535#1" traveltime="0.933776646082"/>
		<edge id="23570717#1" traveltime="3.6454225236"/>
		<edge id="23570717#0" traveltime="1.15555242135"/>
		<edge id="23570717#2" traveltime="1.11837647627"/>
		<edge id="443977183#2" traveltime="1.3485880165"/>
		<edge id="25994517" traveltime="32.1327798686"/>
		<edge id="-23689552#0" traveltime="1.20603041025"/>
		<edge id="258340584" traveltime="9.41328768444"/>
		<edge id="-23785500" traveltime="5.80638114325"/>
		<edge id="4208546" traveltime="12.4555266645"/>
		<edge id="23590869" traveltime="16.7684473916"/>
		<edge id="-32873314#0" traveltime="2.67708240236"/>
		<edge id="-32873314#1" traveltime="11.7682331472"/>
		<edge id="358228122" traveltime="0.671949476014"/>
		<edge id="358228123" traveltime="1.04555913298"/>
		<edge id="-9702304#7" traveltime="1.79246666375"/>
		<edge id="358228121" traveltime="0.789157997044"/>
		<edge id="-9702304#1" traveltime="11.8684666613"/>
		<edge id="-9702304#0" traveltime="0.924752473862"/>
		<edge id="-9702304#3" traveltime="8.76474908434"/>
		<edge id="-9702304#2" traveltime="1.69563088339"/>
		<edge id="-9702304#8" traveltime="4.04931439946"/>
		<edge id="24031605#0" traveltime="10.936493842"/>
		<edge id="24031605#1" traveltime="13.0926482038"/>
		<edge id="-361775195" traveltime="6.96068559893"/>
		<edge id="23570749#0" traveltime="7.86632179353"/>
		<edge id="23570749#1" traveltime="0.466992719027"/>
		<edge id="162845089" traveltime="1.01692680188"/>
		<edge id="162845083" traveltime="0.994372465788"/>
		<edge id="162845082" traveltime="0.0276566809245"/>
		<edge id="162845081" traveltime="2.29612837161"/>
		<edge id="162845086" traveltime="14.5391349996"/>
		<edge id="162845084" traveltime="1.91738653516"/>
		<edge id="23912440" traveltime="12.4428805155"/>
		<edge id="46832782#1" traveltime="0.149061689316"/>
		<edge id="198862612" traveltime="9.42904548997"/>
		<edge id="220958533" traveltime="0.891040338038"/>
		<edge id="220958532" traveltime="0.592086833154"/>
		<edge id="220958531" traveltime="0.934071723418"/>
		<edge id="23689393#0" traveltime="4.1804537133"/>
		<edge id="23689393#1" traveltime="4.95622121076"/>
		<edge id="23689393#2" traveltime="2.31004189772"/>
		<edge id="220958534" traveltime="1.27277987852"/>
		<edge id="23569642#0" traveltime="4.88667406721"/>
		<edge id="23570187#0" traveltime="3.91105411236"/>
		<edge id="23570187#1" traveltime="10.2257495555"/>
		<edge id="23570187#2" traveltime="6.18484054445"/>
		<edge id="23570187#3" traveltime="4.75076203711"/>
		<edge id="23570187#4" traveltime="3.68484922147"/>
		<edge id="-101233479" traveltime="24.1019193179"/>
		<edge id="23785487#7" traveltime="11.3900028817"/>
		<edge id="23785487#6" traveltime="0.333709443421"/>
		<edge id="31501529" traveltime="5.13970789234"/>
		<edge id="198862615" traveltime="4.17213371398"/>
		<edge id="23785487#3" traveltime="15.0778029779"/>
		<edge id="23785487#2" traveltime="0.500125369458"/>
		<edge id="23785487#1" traveltime="13.0864369328"/>
		<edge id="23785487#0" traveltime="4.36721313524"/>
		<edge id="71901025#0" traveltime="12.4964223548"/>
		<edge id="71901025#1" traveltime="4.56597673492"/>
		<edge id="23570103#0" traveltime="12.8735563023"/>
		<edge id="23570103#1" traveltime="9.54622794191"/>
		<edge id="23502729" traveltime="0.0316516506706"/>
		<edge id="45547150#0" traveltime="18.9478566942"/>
		<edge id="45547150#1" traveltime="12.1760040179"/>
		<edge id="23703915" traveltime="30.7419502809"/>
		<edge id="90282229" traveltime="8.71669818307"/>
		<edge id="445309968#2" traveltime="13.6734460226"/>
		<edge id="445309968#3" traveltime="1.11486288503"/>
		<edge id="445309968#0" traveltime="1.63056488309"/>
		<edge id="445309968#1" traveltime="17.2567209619"/>
		<edge id="32113739#4" traveltime="0.0305572945997"/>
		<edge id="32113739#0" traveltime="18.0681862564"/>
		<edge id="32113739#1" traveltime="12.3134820958"/>
		<edge id="32113739#2" traveltime="3.39545708539"/>
		<edge id="32113739#3" traveltime="0.745227187718"/>
		<edge id="285676730#0" traveltime="10.2357097938"/>
		<edge id="285676730#1" traveltime="5.98351387874"/>
		<edge id="31520214#1" traveltime="2.28850207036"/>
		<edge id="31520214#0" traveltime="0.606398056584"/>
		<edge id="23841661#0" traveltime="14.3981941842"/>
		<edge id="23841661#1" traveltime="5.37117125756"/>
		<edge id="193664680" traveltime="4.50190159526"/>
		<edge id="-243046551" traveltime="0.00982571057873"/>
		<edge id="27329978#0" traveltime="15.0812119824"/>
		<edge id="27329978#1" traveltime="0.142822437534"/>
		<edge id="246800024" traveltime="1.95910213957"/>
		<edge id="246800023" traveltime="6.32395678579"/>
		<edge id="25994327#0" traveltime="17.7283823442"/>
		<edge id="25994327#1" traveltime="10.5680913282"/>
		<edge id="25994327#2" traveltime="5.93414706292"/>
		<edge id="23628723" traveltime="2.93434357583"/>
		<edge id="31520096" traveltime="0.508684547257"/>
		<edge id="9702506" traveltime="7.27279977295"/>
		<edge id="-25995141#1" traveltime="18.991062463"/>
		<edge id="-25995141#3" traveltime="22.8105505322"/>
		<edge id="23570716#0" traveltime="1.92176640437"/>
		<edge id="23570716#1" traveltime="3.36573279498"/>
		<edge id="23570716#2" traveltime="1.47825217319"/>
		<edge id="-25995141#2" traveltime="1.96037879449"/>
		<edge id="23820393" traveltime="4.90932658873"/>
		<edge id="403906249" traveltime="0.386471061192"/>
		<edge id="23785428#2" traveltime="0.145832343718"/>
		<edge id="257657826#0" traveltime="10.0990706185"/>
		<edge id="-23590694" traveltime="8.47607420896"/>
		<edge id="-215446160#2" traveltime="1.54629835799"/>
		<edge id="-215446160#1" traveltime="6.24827532456"/>
		<edge id="-215446160#0" traveltime="2.62657894923"/>
		<edge id="23569674#4" traveltime="3.23182245959"/>
		<edge id="23569674#3" traveltime="8.4049101313"/>
		<edge id="23569674#2" traveltime="8.18481082469"/>
		<edge id="23569674#1" traveltime="7.06610395831"/>
		<edge id="23569674#0" traveltime="1.22790970175"/>
		<edge id="24228720#4" traveltime="10.7640570159"/>
		<edge id="24228720#5" traveltime="9.43310055141"/>
		<edge id="24228720#6" traveltime="10.4566242777"/>
		<edge id="24228720#7" traveltime="12.4812976699"/>
		<edge id="24228720#0" traveltime="11.5961350216"/>
		<edge id="24228720#1" traveltime="10.3503842804"/>
		<edge id="24228720#2" traveltime="0.937128556051"/>
		<edge id="24228720#3" traveltime="0.449221510435"/>
		<edge id="24228720#8" traveltime="0.416829258075"/>
		<edge id="24228720#9" traveltime="6.15992898078"/>
		<edge id="23570801#2" traveltime="18.0163637392"/>
		<edge id="23570801#1" traveltime="5.32408990485"/>
		<edge id="23570801#0" traveltime="12.8878659976"/>
		<edge id="23551883#0" traveltime="13.6460940971"/>
		<edge id="23551883#1" traveltime="8.71392039483"/>
		<edge id="443977183#8" traveltime="14.8429445948"/>
		<edge id="443977183#9" traveltime="0.130319142646"/>
		<edge id="443977183#6" traveltime="0.510100186593"/>
		<edge id="443977183#7" traveltime="7.69221020616"/>
		<edge id="443977183#4" traveltime="0.783028182787"/>
		<edge id="443977183#5" traveltime="9.83519079089"/>
		<edge id="349935133#0" traveltime="2.03726867406"/>
		<edge id="349935133#1" traveltime="24.9530472833"/>
		<edge id="443977183#0" traveltime="1.43482640849"/>
		<edge id="443977183#1" traveltime="5.60073431113"/>
		<edge id="31520098#1" traveltime="7.24427797211"/>
		<edge id="31520098#0" traveltime="0.576040889712"/>
		<edge id="-27268914" traveltime="8.07389270077"/>
		<edge id="-27268910" traveltime="13.6392405054"/>
		<edge id="23569655" traveltime="7.19212859241"/>
		<edge id="23569651" traveltime="5.106151468"/>
		<edge id="-23785391" traveltime="11.2522674215"/>
		<edge id="257657826#1" traveltime="26.767325413"/>
		<edge id="24260015" traveltime="16.2726752955"/>
		<edge id="-23818221#0" traveltime="11.7096067493"/>
		<edge id="-23818221#1" traveltime="1.0214723815"/>
		<edge id="-23572294#0" traveltime="6.85486153207"/>
	</interval>
</meandata>
